{
  "_class": "text",
  "attributedString": {
    "_class": "attributedString",
    "attributes": [
      {
        "_class": "stringAttribute",
        "attributes": {
          "MSAttributedStringColorAttribute": {
            "_class": "color",
            "alpha": 1,
            "blue": 0.28,
            "green": 0.28,
            "red": 0.28
          },
          "MSAttributedStringFontAttribute": {
            "_class": "fontDescriptor",
            "attributes": {
              "name": "SourceSansPro-Regular",
              "size": 13
            }
          },
          "paragraphStyle": {
            "_class": "paragraphStyle",
            "alignment": 0
          }
        },
        "length": 53,
        "location": 0
      }
    ],
    "string": "Nailing It On The Head With Free Internet Advertising"
  },
  "automaticallyDrawOnUnderlyingPath": false,
  "do_objectID": "0CB484F4-C402-42C3-A004-7EE28CA4A820",
  "dontSynchroniseWithSymbol": false,
  "exportOptions": {
    "_class": "exportOptions",
    "do_objectID": "9BF088BD-ED48-4D77-A15D-C266A956A91B",
    "exportFormats": [
    ],
    "includedLayerIds": [
    ],
    "layerOptions": 0,
    "shouldTrim": false
  },
  "frame": {
    "_class": "rect",
    "constrainProportions": false,
    "do_objectID": "46C9E125-A389-4D2C-A446-110AAEFFB4B5",
    "height": 34,
    "width": 220,
    "x": 41,
    "y": 84
  },
  "glyphBounds": "{{1, 3}, {174, 30}}",
  "isFlippedHorizontal": false,
  "isFlippedVertical": false,
  "isLocked": false,
  "isVisible": true,
  "layerListExpandedType": 0,
  "lineSpacingBehaviour": 2,
  "name": "Nailing It On The He Copy",
  "nameIsFixed": false,
  "resizingConstraint": 47,
  "resizingType": 0,
  "rotation": 0,
  "shouldBreakMaskChain": false,
  "style": {
    "_class": "style",
    "do_objectID": "90E9027A-EEE1-4FCE-B189-5CCAEB1A322A",
    "endDecorationType": 0,
    "miterLimit": 10,
    "sharedObjectID": "CFF24D79-0084-41E6-BDBC-A3A359EB237D",
    "startDecorationType": 0,
    "textStyle": {
      "_class": "textStyle",
      "do_objectID": "00F1C8F6-B570-4EAB-84C5-C2D16631CE66",
      "encodedAttributes": {
        "MSAttributedStringColorAttribute": {
          "_class": "color",
          "alpha": 1,
          "blue": 0.28,
          "green": 0.28,
          "red": 0.28
        },
        "MSAttributedStringFontAttribute": {
          "_class": "fontDescriptor",
          "attributes": {
            "name": "SourceSansPro-Regular",
            "size": 13
          }
        },
        "paragraphStyle": {
          "_class": "paragraphStyle",
          "alignment": 0
        }
      },
      "verticalAlignment": 0
    }
  },
  "textBehaviour": 1,
  "userInfo": {
    "com.invisionlabs.duplicate": {
      "type-duplicate": {
        "action": "article",
        "options": {
          "section": "advertising",
          "type": "title"
        },
        "title": "Advertising"
      }
    }
  }
}