{
  "_class": "text",
  "attributedString": {
    "_class": "attributedString",
    "attributes": [
      {
        "_class": "stringAttribute",
        "attributes": {
          "MSAttributedStringColorAttribute": {
            "_class": "color",
            "alpha": 1,
            "blue": 0,
            "green": 0,
            "red": 0
          },
          "MSAttributedStringFontAttribute": {
            "_class": "fontDescriptor",
            "attributes": {
              "name": "SourceSansPro-Semibold",
              "size": 18
            }
          },
          "paragraphStyle": {
            "_class": "paragraphStyle",
            "alignment": 0
          }
        },
        "length": 26,
        "location": 0
      }
    ],
    "string": "Frequently Asked Questions"
  },
  "automaticallyDrawOnUnderlyingPath": false,
  "do_objectID": "4A3693FF-00EC-4564-8C0B-74AC72533848",
  "dontSynchroniseWithSymbol": false,
  "exportOptions": {
    "_class": "exportOptions",
    "do_objectID": "52FB13B9-8646-461B-8636-7A6ADBA7BB7D",
    "exportFormats": [
    ],
    "includedLayerIds": [
    ],
    "layerOptions": 0,
    "shouldTrim": false
  },
  "frame": {
    "_class": "rect",
    "constrainProportions": false,
    "do_objectID": "82B6D12F-573C-4487-A432-AEEB8927076C",
    "height": 23,
    "width": 344,
    "x": 468,
    "y": 447
  },
  "glyphBounds": "{{1, 5}, {214, 17}}",
  "isFlippedHorizontal": false,
  "isFlippedVertical": false,
  "isLocked": false,
  "isVisible": true,
  "layerListExpandedType": 0,
  "lineSpacingBehaviour": 2,
  "name": "Frequently Asked Que",
  "nameIsFixed": false,
  "resizingConstraint": 47,
  "resizingType": 0,
  "rotation": 0,
  "shouldBreakMaskChain": false,
  "style": {
    "_class": "style",
    "contextSettings": {
      "_class": "graphicsContextSettings",
      "blendMode": 0,
      "do_objectID": "D2872DFA-1575-4A07-8087-F0EB7BCBCEA2",
      "opacity": 0.5
    },
    "do_objectID": "8472D2F7-22C3-4891-B117-1CB4BE9EAEB4",
    "endDecorationType": 0,
    "miterLimit": 10,
    "sharedObjectID": "76889896-00B0-46AF-9616-57C1E27F6D2A",
    "startDecorationType": 0,
    "textStyle": {
      "_class": "textStyle",
      "do_objectID": "A36108FE-3AA9-489F-8851-B2011BF57CA8",
      "encodedAttributes": {
        "MSAttributedStringColorAttribute": {
          "_class": "color",
          "alpha": 1,
          "blue": 0,
          "green": 0,
          "red": 0
        },
        "MSAttributedStringFontAttribute": {
          "_class": "fontDescriptor",
          "attributes": {
            "name": "SourceSansPro-Semibold",
            "size": 18
          }
        },
        "paragraphStyle": {
          "_class": "paragraphStyle",
          "alignment": 0
        }
      },
      "verticalAlignment": 0
    }
  },
  "textBehaviour": 1,
  "userInfo": {
    "com.animaapp.stc-sketch-plugin": {
      "kModelPropertiesKey": {
        "isAutoWidth": 0
      }
    }
  }
}