{
  "_class": "shapeGroup",
  "clippingMaskMode": 0,
  "do_objectID": "CD879ACA-80D2-41C9-B909-25B63C4C236E",
  "exportOptions": {
    "_class": "exportOptions",
    "do_objectID": "4BC31195-2157-4A08-9347-89779367F9FF",
    "exportFormats": [
    ],
    "includedLayerIds": [
    ],
    "layerOptions": 0,
    "shouldTrim": false
  },
  "frame": {
    "_class": "rect",
    "constrainProportions": false,
    "do_objectID": "597C501E-1D6C-477C-94BC-E630C10CE8D3",
    "height": 5,
    "width": 10,
    "x": 411,
    "y": 46
  },
  "hasClickThrough": false,
  "hasClippingMask": false,
  "isFlippedHorizontal": false,
  "isFlippedVertical": false,
  "isLocked": false,
  "isVisible": true,
  "layerListExpandedType": 0,
  "layers": [
    {
      "class": "shapePath",
      "id": "22AA99C4-73D4-40DD-A63A-62948868B98A"
    }
  ],
  "name": "Shape Copy 2",
  "nameIsFixed": false,
  "resizingConstraint": 45,
  "resizingType": 3,
  "rotation": 0,
  "shouldBreakMaskChain": false,
  "style": {
    "_class": "style",
    "do_objectID": "7E7A5A27-7D52-4776-9975-6C19CD20D823",
    "endDecorationType": 0,
    "fills": [
      {
        "_class": "fill",
        "color": {
          "_class": "color",
          "alpha": 1,
          "blue": 0,
          "green": 0,
          "red": 0
        },
        "fillType": 0,
        "isEnabled": true,
        "noiseIndex": 0,
        "noiseIntensity": 0,
        "patternFillType": 0,
        "patternTileScale": 1
      }
    ],
    "miterLimit": 10,
    "sharedObjectID": "A93742BB-00F9-4F61-A4D3-18497765722F",
    "startDecorationType": 0
  },
  "windingRule": 1
}