{
  "_class": "text",
  "attributedString": {
    "_class": "attributedString",
    "attributes": [
      {
        "_class": "stringAttribute",
        "attributes": {
          "MSAttributedStringColorAttribute": {
            "_class": "color",
            "alpha": 1,
            "blue": 0,
            "green": 0,
            "red": 0
          },
          "MSAttributedStringFontAttribute": {
            "_class": "fontDescriptor",
            "attributes": {
              "name": "SourceSansPro-Regular",
              "size": 16
            }
          },
          "paragraphStyle": {
            "_class": "paragraphStyle",
            "alignment": 0,
            "maximumLineHeight": 24,
            "minimumLineHeight": 24
          }
        },
        "length": 519,
        "location": 0
      }
    ],
    "string": "If you are in the market for a computer, there are a number of factors to consider. Will it be used for your home, your office or perhaps even your home office combo? First off, you will need to set a budget for your new purchase before deciding whether to shop for notebook or desktop computers. Many offices use desktop computers because they are not intended to be moved around a lot. In addition, affordability often plays a large role in someone’s decision as to whether to purchase notebook or desktop computers.\n"
  },
  "automaticallyDrawOnUnderlyingPath": false,
  "do_objectID": "352D1EC7-4DC6-4C0F-BA53-BD1236C75444",
  "dontSynchroniseWithSymbol": false,
  "exportOptions": {
    "_class": "exportOptions",
    "exportFormats": [
    ],
    "includedLayerIds": [
    ],
    "layerOptions": 0,
    "shouldTrim": false
  },
  "frame": {
    "_class": "rect",
    "constrainProportions": false,
    "height": 130,
    "width": 712,
    "x": 192,
    "y": 618
  },
  "glyphBounds": "{{0, 6}, {710, 112}}",
  "isFlippedHorizontal": false,
  "isFlippedVertical": false,
  "isLocked": false,
  "isVisible": true,
  "layerListExpandedType": 0,
  "lineSpacingBehaviour": 2,
  "name": "If you are in the ma",
  "nameIsFixed": false,
  "resizingConstraint": 63,
  "resizingType": 0,
  "rotation": 0,
  "shouldBreakMaskChain": false,
  "style": {
    "sharedObjectID": "23EA0509-3869-43DE-BCA9-7E5F26CC7656"
  },
  "textBehaviour": 2,
  "userInfo": {
    "com.animaapp.stc-sketch-plugin": {
      "kModelPropertiesKey": {
        "isAutoWidth": 0
      }
    },
    "com.invisionlabs.duplicate": {
      "type-duplicate": {
        "action": "article",
        "options": {
          "section": "technology",
          "type": "body"
        },
        "title": "Technology"
      }
    }
  }
}