{
  "_class": "shapeGroup",
  "clippingMaskMode": 0,
  "do_objectID": "7B262152-ECE3-4707-A742-1A3B2E809ADF",
  "exportOptions": {
    "_class": "exportOptions",
    "do_objectID": "09978AD4-3174-4BDA-A1C8-4CE3CD09E1C4",
    "exportFormats": [
    ],
    "includedLayerIds": [
    ],
    "layerOptions": 0,
    "shouldTrim": false
  },
  "frame": {
    "_class": "rect",
    "constrainProportions": false,
    "do_objectID": "4C53CA64-019B-49D2-9767-8D8C05F86320",
    "height": 24,
    "width": 24,
    "x": 0,
    "y": 0
  },
  "hasClickThrough": false,
  "hasClippingMask": false,
  "isFlippedHorizontal": false,
  "isFlippedVertical": false,
  "isLocked": false,
  "isVisible": true,
  "layerListExpandedType": 1,
  "layers": [
    {
      "class": "shapePath",
      "id": "D5BFB733-D0A6-4506-84AC-B3AD4742D8F7"
    }
  ],
  "name": "Shape",
  "nameIsFixed": false,
  "resizingConstraint": 63,
  "resizingType": 0,
  "rotation": 0,
  "shouldBreakMaskChain": false,
  "style": {
    "_class": "style",
    "do_objectID": "F6E77949-23A0-4181-B7F5-C2804AE49AFE",
    "endDecorationType": 0,
    "miterLimit": 10,
    "startDecorationType": 0
  },
  "windingRule": 1
}