{
  "_class": "shapePath",
  "booleanOperation": -1,
  "do_objectID": "9DDCB505-6235-4A1D-AD59-E73E6FD8BDF7",
  "edited": true,
  "exportOptions": {
    "_class": "exportOptions",
    "do_objectID": "FE58A5D1-24B8-45B5-8044-817CD1B6A61A",
    "exportFormats": [
    ],
    "includedLayerIds": [
    ],
    "layerOptions": 0,
    "shouldTrim": false
  },
  "frame": {
    "_class": "rect",
    "constrainProportions": false,
    "do_objectID": "086F1DB7-093C-4256-89C4-92A2EFBEE7A6",
    "height": 2,
    "width": 1079,
    "x": 0,
    "y": 0
  },
  "isClosed": false,
  "isFlippedHorizontal": false,
  "isFlippedVertical": false,
  "isLocked": false,
  "isVisible": true,
  "layerListExpandedType": 0,
  "name": "Path",
  "nameIsFixed": false,
  "pointRadiusBehaviour": 1,
  "points": [
    {
      "_class": "curvePoint",
      "cornerRadius": 0,
      "curveFrom": "{0.0005202913631633711, 0.75}",
      "curveMode": 1,
      "curveTo": "{0.0005202913631633711, 0.75}",
      "hasCurveFrom": false,
      "hasCurveTo": false,
      "point": "{0, 0.5}"
    },
    {
      "_class": "curvePoint",
      "cornerRadius": 0,
      "curveFrom": "{0.0015608740894901129, 1.25}",
      "curveMode": 1,
      "curveTo": "{0.0015608740894901129, 1.25}",
      "hasCurveFrom": false,
      "hasCurveTo": false,
      "point": "{0.99947970863683666, 0.5}"
    }
  ],
  "resizingConstraint": 63,
  "resizingType": 0,
  "rotation": 0,
  "shouldBreakMaskChain": false
}