{
  "_class": "group",
  "do_objectID": "3E6A73D4-FD7C-4A03-A69C-98B59383BB8C",
  "exportOptions": {
    "_class": "exportOptions",
    "do_objectID": "EF4D954E-88E2-429E-82AE-4239ACBF1E2E",
    "exportFormats": [
    ],
    "includedLayerIds": [
    ],
    "layerOptions": 0,
    "shouldTrim": false
  },
  "frame": {
    "_class": "rect",
    "constrainProportions": true,
    "do_objectID": "4ED4B7E0-0B79-4F22-9385-CB3CDC7D1AE8",
    "height": 16,
    "width": 16,
    "x": 144,
    "y": 4
  },
  "hasClickThrough": false,
  "isFlippedHorizontal": false,
  "isFlippedVertical": false,
  "isLocked": false,
  "isVisible": true,
  "layerListExpandedType": 0,
  "layers": [
    {
      "class": "shapeGroup",
      "id": "760D4F5B-0547-44EE-A405-6FE6EAEE5909"
    },
    {
      "class": "shapeGroup",
      "id": "42F38D8E-C52A-43F0-8F77-AC6E575245AB"
    }
  ],
  "name": "ic_navigate_next_black_24px copy 11",
  "nameIsFixed": false,
  "resizingConstraint": 63,
  "resizingType": 0,
  "rotation": 0,
  "shouldBreakMaskChain": false,
  "style": {
    "_class": "style",
    "do_objectID": "0505AC78-7077-4672-A240-B27DCB90B6E1",
    "endDecorationType": 0,
    "miterLimit": 10,
    "startDecorationType": 0
  },
  "userInfo": {
    "com.animaapp.stc-sketch-plugin": {
      "kModelPropertiesKey": {
        "constraints": {
          "aspectRatio": {
            "constant": 16,
            "enabled": 1,
            "modelID": "constraint_df8609e5-cf3a-4ecb-aa1f-62c1653d1631",
            "model_class": "ADModelConstraint",
            "model_version": 0.1,
            "multiplier": 16
          },
          "automatic": 1,
          "modelID": "viewConstraints_3430dc27-970c-4a1a-914e-321e49e46627",
          "model_class": "ADModelViewConstraints",
          "model_version": 0.1,
          "scaleFactor": 1
        }
      }
    }
  }
}